__init__.py
main.py
models.py
utils.py
src/__init__.py
src/main.py
src/models.py
src/utils.py
git_assigned_pr_viewer-0.1.1.dist-info/METADATA
git_assigned_pr_viewer-0.1.1.dist-info/WHEEL
git_assigned_pr_viewer-0.1.1.dist-info/entry_points.txt
git_assigned_pr_viewer-0.1.1.dist-info/top_level.txt
git_assigned_pr_viewer-0.1.1.dist-info/RECORD
